archivist/__init__.py
archivist/definitions.py
archivist/logger_builder.py
archivist/templates/logging_console.yml
archivist/templates/logging_rotating.yml
archivist/templates/logging_scheduled.yml
archivist_logger-0.1.1.dist-info/LICENSE
archivist_logger-0.1.1.dist-info/METADATA
archivist_logger-0.1.1.dist-info/WHEEL
archivist_logger-0.1.1.dist-info/top_level.txt
archivist_logger-0.1.1.dist-info/RECORD
