Metadata-Version: 2.1
Name: archivist-logger
Version: 0.1.1
Summary: Fast building of logger from common templates
Author-email: Romain Damian <damian.romain@gmail.com>
License: MIT License
License-File: LICENSE
Requires-Dist: pyyaml
